mongodb_connector/__init__.py
mongodb_connector/mongo_crud.py
MongoConn-1.0.0.dist-info/LICENSE
MongoConn-1.0.0.dist-info/METADATA
MongoConn-1.0.0.dist-info/WHEEL
MongoConn-1.0.0.dist-info/top_level.txt
MongoConn-1.0.0.dist-info/RECORD
