Metadata-Version: 2.1
Name: MongoConn
Version: 1.0.0
Summary: A small python package for mongodb connector
Home-page: https://github.com/Madhabpoulik/MongoDB_connector
Author: Madhabpoulik
Author-email: madhabpoulik97@gmail.com
License: MIT
Project-URL: Bug Tracker, https://github.com/Madhabpoulik/MongoDB_connector/issues
Classifier: Programming Language :: Python :: 3.6
Classifier: Programming Language :: Python :: 3.7
Classifier: Programming Language :: Python :: 3.8
Classifier: Programming Language :: Python :: 3.9
Classifier: Programming Language :: Python :: 3.10
Classifier: Programming Language :: Python :: 3.11
Classifier: Operating System :: OS Independent
Requires-Python: >=3.6
License-File: LICENSE
Requires-Dist: pymongo>=4.0
Provides-Extra: testing
Requires-Dist: pytest==7.2.0; extra == "testing"
Requires-Dist: mypy==0.991; extra == "testing"
Requires-Dist: flake8==5.0.4; extra == "testing"
Requires-Dist: tox==3.25.1; extra == "testing"
Requires-Dist: black==22.10.0; extra == "testing"
